hitori/__init__.py
hitori/py.typed
hitori-1.0.0.dist-info/licenses/LICENSE.md
hitori-1.0.0.dist-info/METADATA
hitori-1.0.0.dist-info/WHEEL
hitori-1.0.0.dist-info/top_level.txt
hitori-1.0.0.dist-info/RECORD
