Metadata-Version: 2.4
Name: hitori
Version: 1.0.0
Summary: Parsing and serializing Sakura Expressions
Author-email: Hannes Braun <hannes@hannesbraun.net>
License-Expression: BlueOak-1.0.0
Project-URL: homepage, https://git.sr.ht/~hannes/hitori
Project-URL: documentation, https://hannesbraun.net/share/doc/hitori/index.html
Project-URL: repository, https://git.sr.ht/~hannes/hitori
Project-URL: changelog, https://git.sr.ht/~hannes/hitori/refs
Keywords: Sakura Expressions,S-Expression,Parser
Classifier: Development Status :: 5 - Production/Stable
Classifier: Intended Audience :: Developers
Classifier: Programming Language :: Python
Classifier: Topic :: Software Development
Requires-Python: >=3.12
License-File: LICENSE.md
Dynamic: license-file
